mtui/__init__.py
mtui/auth.py
mtui/config.py
mtui/database.py
mtui/types.py
mtui/api/__init__.py
mtui/api/auth.py
mtui/api/course.py
mtui/api/entities.py
mtui/utils/__init__.py
mtui/utils/crypto.py
mtui/utils/dirs.py
mtui/utils/logging.py
MoodleTUI_common-0.0.2.dist-info/LICENSE
MoodleTUI_common-0.0.2.dist-info/METADATA
MoodleTUI_common-0.0.2.dist-info/WHEEL
MoodleTUI_common-0.0.2.dist-info/top_level.txt
MoodleTUI_common-0.0.2.dist-info/RECORD
