Metadata-Version: 2.1
Name: MoodleTUI-common
Version: 0.0.2
Summary: Backend Library for the MoodleTUI project
Home-page: https://github.com/kiwifuit/MoodleTUI-common
Author: CarbonFodder
Author-email: mahkiwi123@gmail.common
Classifier: Programming Language :: Python :: 3
Classifier: Operating System :: OS Independent
License-File: LICENSE
